Workbook
Name BASIS_FC: Inputs!$B$21
Name BASIS_USD: Inputs!$B$20
Name DF_FC: 'Money Market'!$B$7
Name DF_USD: 'Money Market'!$B$6
Name EUR_BORROW: 'Money Market'!$B$8
Name F0_in: Inputs!$B$8
Name FC_AMT: Inputs!$B$6
Name FV_PREMIUM_CALL: Options!$B$14
Name FV_PREMIUM_PUT: Options!$B$8
Name GRID_MIN: Inputs!$B$23
Name K_CALL: Inputs!$B$12
Name K_PUT: Inputs!$B$11
Name PARITY_CHECK: 'Money Market'!$B$14
Name PARITY_GAP: 'Money Market'!$B$12
Name PARITY_TOL: 'Money Market'!$B$13
Name PREM_CALL: Inputs!$B$14
Name PREM_PUT: Inputs!$B$13
Name PREMIUM_TOTAL_CALL: Options!$B$13
Name PREMIUM_TOTAL_PUT: Options!$B$7
Name PUT_PAYOFF: Options!$B$9
Name R_FC: Inputs!$B$10
Name R_USD: Inputs!$B$9
Name S_T_BASE: Options!$B$6
Name S0_in: Inputs!$B$7
Name STEP_FRAC: Inputs!$B$22
Name T_DAYS: Inputs!$B$15
Name USD_FWD: Forward!$B$9
Name USD_MM: 'Money Market'!$B$10
Name USD_NO_HEDGE_BASE: Sensitivity!$B$6
Name USD_PUT_BASE: Options!$B$10
Name USD_PUT_FLOOR: Options!$B$11
Name USD_TODAY: 'Money Market'!$B$9

Sheet Cover
A1: Scenario 4 — EUR Receivable FX Hedge Model
A2: Stage 4 Market Data Population • Formula-driven treasury decision model
A4: Scenario | B4: U.S. Aerospace Manufacturer — €20,000,000 receivable
A5: Author | B5: Kiley Gennerman
A6: Model date | B6: 2026-08-02
A7: Settlement horizon | B7: 365 days / one year
A8: Model status | B8: LIVE — Stage 4 market data populated 2026-08-02 (close 2026-07-31)
A10: Data Provenance and Use
A11: Stage 4 market inputs are dated and documented in data/2026-08-02-gennerman-market-data.md. EUR/USD spot uses the ECB reference rate; the USD rate uses the U.S. 1-year Treasury CMT; the EUR-rate proxy is the ECB deposit facility. The one-year forward is CIP-implied from those inputs; option premia remain the required scenario assumption. This workbook is an analytical model, not trade authorization.
A16: Executive Outputs (linked to model)
A17: Metric | B17: Value
A18: Locked forward proceeds | B18: =USD_FWD -> 23300438
A19: Money-market proceeds | B19: =USD_MM -> 23300438
A20: Put floor (net proceeds) | B20: =USD_PUT_FLOOR -> 22429362
A21: Model status | B21: =Checks!F13 -> PASS

Sheet Legend-Key
A1: Legend / Key
A2: Required color convention applied consistently across the workbook
A5: Color | B5: Cell class | C5: Meaning
A6: Yellow | B6: Inputs | C6: Editable market and contract inputs; blue font identifies user-editable values.
A7: Blue | B7: Assumptions | C7: Editable model conventions and sensitivity controls.
A8: Green | B8: Formulas | C8: Formula-driven calculations and passing control cells.
A9: Gray | B9: Outputs | C9: Formula-driven executive outputs and sensitivity results.
A12: Control convention: PASS is green; FAIL is red. All calculated values are formulas. Inputs are centralized on the Inputs tab; do not edit calculation or output cells.

Sheet Inputs
A1: Inputs and Assumptions
A2: Yellow cells contain dated Stage 4 market data; blue cells are model conventions
A4: Market and Contract Inputs — populated 2026-08-02; sources in data memo
A5: Named Range | B5: Value | C5: Unit | D5: Description | E5: Stage 4 source
A6: FC_AMT | B6: 20000000 | C6: EUR | D6: Contractual foreign-currency receivable | E6: Executed customer contract
A7: S0_in | B7: 1.1527 | C7: USD per EUR | D7: EUR/USD spot at model inception | E7: ECB reference rate; 2026-07-27
A8: F0_in | B8: 1.1650219 | C8: USD per EUR | D8: 1-year EUR/USD forward | E8: CIP-implied from S0_in, R_USD, R_FC
A9: R_USD | B9: 0.0405 | C9: Annual % | D9: USD 1-year rate | E9: FRED DGS1 / U.S. Treasury CMT; 2026-07-08
A10: R_FC | B10: 0.02964 | C10: Annual % | D10: EUR reference-rate proxy | E10: ECB deposit facility; effective 2026-06-17
A11: K_PUT | B11: 1.1527 | C11: USD per EUR | D11: EUR put strike | E11: Set near live spot; Treasury convention
A12: K_CALL | B12: 1.1527 | C12: USD per EUR | D12: EUR call strike; reference only | E12: Set near live spot; Treasury convention
A13: PREM_PUT | B13: 0.03 | C13: USD per EUR | D13: Put premium per EUR | E13: Scenario assumption; retail quotes unreliable
A14: PREM_CALL | B14: 0.03 | C14: USD per EUR | D14: Call premium per EUR | E14: Scenario assumption; retail quotes unreliable
A15: T_DAYS | B15: 365 | C15: Days | D15: Days to settlement | E15: Contract date less valuation date
A18: Model Assumptions and Sensitivity Controls
A19: Assumption | B19: Value | C19: Unit | D19: Purpose
A20: BASIS_USD | B20: 360 | C20: Days | D20: ACT/360 simple-interest basis for USD leg
A21: BASIS_FC | B21: 360 | C21: Days | D21: ACT/360 simple-interest basis for EUR leg
A22: STEP_FRAC | B22: 0.01 | C22: % | D22: Sensitivity increment
A23: GRID_MIN | B23: -5 | C23: Steps | D23: Starting sensitivity step; grid ends at +5

Sheet Forward
A1: Forward Hedge
A2: Sell €20,000,000 forward at the matching settlement rate
A4: Forward Calculation
A5: Item | B5: Value | C5: Unit | D5: Formula / audit note
A6: EUR receivable | B6: =FC_AMT -> 20000000 | C6: EUR | D6: =FC_AMT
A7: Forward rate | B7: =F0_in -> 1.1650219 | C7: USD per EUR | D7: =F0_in
A8: Forward contract | B8: Sell EUR / buy USD | C8: Direction | D8: Maturity matches T_DAYS
A9: Locked USD proceeds | B9: =FC_AMT*F0_in -> 23300438 | C9: USD | D9: =FC_AMT*F0_in
A10: Hedge profile | B10: Fixed | C10: USD proceeds | D10: Invariant across S_T scenarios
A11: Input status | B11: Indicative | C11: Stage 4 | D11: Replace F0_in with live matching-tenor quote

Sheet Money Market
A1: Money-Market Hedge
A2: Three explicit steps — borrow EUR, convert to USD, invest USD
A4: Money-Market Calculation and Parity Control
A5: Item | B5: Value | C5: Unit | D5: Formula / audit note
A6: USD accumulation factor (DF_USD) | B6: =1+R_USD*T_DAYS/BASIS_USD -> 1.0410625 | C6: x | D6: =1+R_USD*T_DAYS/BASIS_USD
A7: EUR accumulation factor (DF_FC) | B7: =1+R_FC*T_DAYS/BASIS_FC -> 1.0300517 | C7: x | D7: =1+R_FC*T_DAYS/BASIS_FC
A8: Step 1: borrow EUR PV | B8: =FC_AMT/DF_FC -> 19416502 | C8: EUR | D8: =FC_AMT/DF_FC
A9: Step 2: convert to USD today | B9: =EUR_BORROW*S0_in -> 22381402 | C9: USD | D9: =EUR_BORROW*S0_in
A10: Step 3: invest USD to maturity | B10: =USD_TODAY*DF_USD -> 23300438 | C10: USD | D10: =USD_TODAY*DF_USD
A11: Forward benchmark | B11: =USD_FWD -> 23300438 | C11: USD | D11: =USD_FWD
A12: Parity gap | B12: =USD_MM-USD_FWD -> -3.3527613e-08 | C12: USD | D12: =USD_MM-USD_FWD
A13: Parity tolerance | B13: 1 | C13: USD | D13: Maximum permitted absolute gap
A14: Parity check | B14: =IF(ABS(PARITY_GAP)<=PARITY_TOL,"PASS","FAIL") -> PASS | C14: PASS / FAIL | D14: =ABS(PARITY_GAP)<=PARITY_TOL
A15: Settlement mechanics | B15: Receivable repays EUR borrowing | D15: No residual EUR exposure

Sheet Options
A1: Option Hedges
A2: EUR put protects the receivable; EUR call cost is shown as a payable-reference calculation
A4: Put and Call Premium / Payoff Calculations
A5: Item | B5: Value | C5: Unit | D5: Formula / audit note
A6: Settlement spot (S_T base case) | B6: =S0_in -> 1.1527 | C6: USD per EUR | D6: =S0_in
A7: Put premium total paid today | B7: =PREM_PUT*FC_AMT -> 600000 | C7: USD | D7: =PREM_PUT*FC_AMT
A8: Put premium FV at settlement | B8: =PREMIUM_TOTAL_PUT*DF_USD -> 624637.5 | C8: USD | D8: =PREMIUM_TOTAL_PUT*DF_USD
A9: Put intrinsic payoff | B9: =MAX(0,K_PUT-S_T_BASE)*FC_AMT -> 0 | C9: USD | D9: =MAX(0,K_PUT-S_T_BASE)*FC_AMT
A10: Put net USD proceeds | B10: =S_T_BASE*FC_AMT+PUT_PAYOFF-FV_PREMIUM_PUT -> 22429362 | C10: USD | D10: =S_T_BASE*FC_AMT+PUT_PAYOFF-FV_PREMIUM_PUT
A11: Put floor over sensitivity grid | B11: =MIN(Sensitivity!F13:F23) -> 22429362 | C11: USD | D11: =MIN('Sensitivity'!F13:F23)
A13: Call premium total paid today | B13: =PREM_CALL*FC_AMT -> 600000 | C13: USD | D13: =PREM_CALL*FC_AMT
A14: Call premium FV at settlement | B14: =PREMIUM_TOTAL_CALL*DF_USD -> 624637.5 | C14: USD | D14: =PREMIUM_TOTAL_CALL*DF_USD
A15: Call intrinsic payoff | B15: =MAX(0,S_T_BASE-K_CALL)*FC_AMT -> 0 | C15: USD | D15: =MAX(0,S_T_BASE-K_CALL)*FC_AMT
A16: Call USD cost (payable reference) | B16: =MIN(S_T_BASE,K_CALL)*FC_AMT+FV_PREMIUM_CALL -> 23678638 | C16: USD | D16: =MIN(S_T_BASE,K_CALL)*FC_AMT+FV_PREMIUM_CALL
A17: Exercise logic | B17: Put: exercise below strike; Call: exercise above strike | D17: Call is reference-only for this receivable
A18: Input status | B18: Indicative | C18: Stage 4 | D18: Replace strikes / premiums with executable quotes
A21: Call Reference — Formula-Driven Settlement-Spot Schedule
A22: Step | B22: S_T (USD/EUR) | C22: Call payoff | D22: USD outlay if payable
A23: =Sensitivity!A13 -> -5 | B23: =Sensitivity!B13 -> 1.095065 | C23: =MAX(0,B23-K_CALL)*FC_AMT -> 0 | D23: =MIN(B23,K_CALL)*FC_AMT+FV_PREMIUM_CALL -> 22525938
A24: =Sensitivity!A14 -> -4 | B24: =Sensitivity!B14 -> 1.106592 | C24: =MAX(0,B24-K_CALL)*FC_AMT -> 0 | D24: =MIN(B24,K_CALL)*FC_AMT+FV_PREMIUM_CALL -> 22756478
A25: =Sensitivity!A15 -> -3 | B25: =Sensitivity!B15 -> 1.118119 | C25: =MAX(0,B25-K_CALL)*FC_AMT -> 0 | D25: =MIN(B25,K_CALL)*FC_AMT+FV_PREMIUM_CALL -> 22987018
A26: =Sensitivity!A16 -> -2 | B26: =Sensitivity!B16 -> 1.129646 | C26: =MAX(0,B26-K_CALL)*FC_AMT -> 0 | D26: =MIN(B26,K_CALL)*FC_AMT+FV_PREMIUM_CALL -> 23217558
A27: =Sensitivity!A17 -> -1 | B27: =Sensitivity!B17 -> 1.141173 | C27: =MAX(0,B27-K_CALL)*FC_AMT -> 0 | D27: =MIN(B27,K_CALL)*FC_AMT+FV_PREMIUM_CALL -> 23448098
A28: =Sensitivity!A18 -> 0 | B28: =Sensitivity!B18 -> 1.1527 | C28: =MAX(0,B28-K_CALL)*FC_AMT -> 0 | D28: =MIN(B28,K_CALL)*FC_AMT+FV_PREMIUM_CALL -> 23678638
A29: =Sensitivity!A19 -> 1 | B29: =Sensitivity!B19 -> 1.164227 | C29: =MAX(0,B29-K_CALL)*FC_AMT -> 230540 | D29: =MIN(B29,K_CALL)*FC_AMT+FV_PREMIUM_CALL -> 23678638
A30: =Sensitivity!A20 -> 2 | B30: =Sensitivity!B20 -> 1.175754 | C30: =MAX(0,B30-K_CALL)*FC_AMT -> 461080 | D30: =MIN(B30,K_CALL)*FC_AMT+FV_PREMIUM_CALL -> 23678638
A31: =Sensitivity!A21 -> 3 | B31: =Sensitivity!B21 -> 1.187281 | C31: =MAX(0,B31-K_CALL)*FC_AMT -> 691620 | D31: =MIN(B31,K_CALL)*FC_AMT+FV_PREMIUM_CALL -> 23678638
A32: =Sensitivity!A22 -> 4 | B32: =Sensitivity!B22 -> 1.198808 | C32: =MAX(0,B32-K_CALL)*FC_AMT -> 922160 | D32: =MIN(B32,K_CALL)*FC_AMT+FV_PREMIUM_CALL -> 23678638
A33: =Sensitivity!A23 -> 5 | B33: =Sensitivity!B23 -> 1.210335 | C33: =MAX(0,B33-K_CALL)*FC_AMT -> 1152700 | D33: =MIN(B33,K_CALL)*FC_AMT+FV_PREMIUM_CALL -> 23678638

Sheet Sensitivity
A1: Sensitivity — Settlement EUR/USD ±5%
A2: Formula-driven eleven-row comparison; higher USD proceeds are better for this receivable
A4: Strategy Summary (Gray Outputs)
A5: Metric | B5: Value
A6: No-hedge base proceeds | B6: =S_T_BASE*FC_AMT -> 23054000
A7: Forward locked proceeds | B7: =USD_FWD -> 23300438
A8: Money-market proceeds | B8: =USD_MM -> 23300438
A9: Put base proceeds | B9: =USD_PUT_BASE -> 22429362
A11: Sensitivity Results
A12: Step | B12: S_T (USD/EUR) | C12: USD_NO_HEDGE | D12: USD_FWD | E12: USD_MM | F12: USD_PUT | G12: HEDGE_VALUE_FWD | H12: HEDGE_VALUE_MM | I12: HEDGE_VALUE_PUT | J12: OVERALL_WINNER
A13: =GRID_MIN -> -5 | B13: =S0_in*(1+A13*STEP_FRAC) -> 1.095065 | C13: =B13*FC_AMT -> 21901300 | D13: =USD_FWD -> 23300438 | E13: =USD_MM -> 23300438 | F13: =MAX(B13,K_PUT)*FC_AMT-FV_PREMIUM_PUT -> 22429362 | G13: =D13-C13 -> 1399137.9 | H13: =E13-C13 -> 1399137.9 | I13: =F13-C13 -> 528062.5 | J13: =IF(C13=MAX(C13:F13),"No Hedge",IF(D13=MAX(C13:F13),"Forward",IF(E13=MAX(C13:F13),"Money Market","Put"))) -> Forward
A14: =A13+1 -> -4 | B14: =S0_in*(1+A14*STEP_FRAC) -> 1.106592 | C14: =B14*FC_AMT -> 22131840 | D14: =USD_FWD -> 23300438 | E14: =USD_MM -> 23300438 | F14: =MAX(B14,K_PUT)*FC_AMT-FV_PREMIUM_PUT -> 22429362 | G14: =D14-C14 -> 1168597.9 | H14: =E14-C14 -> 1168597.9 | I14: =F14-C14 -> 297522.5 | J14: =IF(C14=MAX(C14:F14),"No Hedge",IF(D14=MAX(C14:F14),"Forward",IF(E14=MAX(C14:F14),"Money Market","Put"))) -> Forward
A15: =A14+1 -> -3 | B15: =S0_in*(1+A15*STEP_FRAC) -> 1.118119 | C15: =B15*FC_AMT -> 22362380 | D15: =USD_FWD -> 23300438 | E15: =USD_MM -> 23300438 | F15: =MAX(B15,K_PUT)*FC_AMT-FV_PREMIUM_PUT -> 22429362 | G15: =D15-C15 -> 938057.88 | H15: =E15-C15 -> 938057.88 | I15: =F15-C15 -> 66982.5 | J15: =IF(C15=MAX(C15:F15),"No Hedge",IF(D15=MAX(C15:F15),"Forward",IF(E15=MAX(C15:F15),"Money Market","Put"))) -> Forward
A16: =A15+1 -> -2 | B16: =S0_in*(1+A16*STEP_FRAC) -> 1.129646 | C16: =B16*FC_AMT -> 22592920 | D16: =USD_FWD -> 23300438 | E16: =USD_MM -> 23300438 | F16: =MAX(B16,K_PUT)*FC_AMT-FV_PREMIUM_PUT -> 22429362 | G16: =D16-C16 -> 707517.88 | H16: =E16-C16 -> 707517.88 | I16: =F16-C16 -> -163557.5 | J16: =IF(C16=MAX(C16:F16),"No Hedge",IF(D16=MAX(C16:F16),"Forward",IF(E16=MAX(C16:F16),"Money Market","Put"))) -> Forward
A17: =A16+1 -> -1 | B17: =S0_in*(1+A17*STEP_FRAC) -> 1.141173 | C17: =B17*FC_AMT -> 22823460 | D17: =USD_FWD -> 23300438 | E17: =USD_MM -> 23300438 | F17: =MAX(B17,K_PUT)*FC_AMT-FV_PREMIUM_PUT -> 22429362 | G17: =D17-C17 -> 476977.88 | H17: =E17-C17 -> 476977.88 | I17: =F17-C17 -> -394097.5 | J17: =IF(C17=MAX(C17:F17),"No Hedge",IF(D17=MAX(C17:F17),"Forward",IF(E17=MAX(C17:F17),"Money Market","Put"))) -> Forward
A18: =A17+1 -> 0 | B18: =S0_in*(1+A18*STEP_FRAC) -> 1.1527 | C18: =B18*FC_AMT -> 23054000 | D18: =USD_FWD -> 23300438 | E18: =USD_MM -> 23300438 | F18: =MAX(B18,K_PUT)*FC_AMT-FV_PREMIUM_PUT -> 22429362 | G18: =D18-C18 -> 246437.88 | H18: =E18-C18 -> 246437.88 | I18: =F18-C18 -> -624637.5 | J18: =IF(C18=MAX(C18:F18),"No Hedge",IF(D18=MAX(C18:F18),"Forward",IF(E18=MAX(C18:F18),"Money Market","Put"))) -> Forward
A19: =A18+1 -> 1 | B19: =S0_in*(1+A19*STEP_FRAC) -> 1.164227 | C19: =B19*FC_AMT -> 23284540 | D19: =USD_FWD -> 23300438 | E19: =USD_MM -> 23300438 | F19: =MAX(B19,K_PUT)*FC_AMT-FV_PREMIUM_PUT -> 22659903 | G19: =D19-C19 -> 15897.883 | H19: =E19-C19 -> 15897.883 | I19: =F19-C19 -> -624637.5 | J19: =IF(C19=MAX(C19:F19),"No Hedge",IF(D19=MAX(C19:F19),"Forward",IF(E19=MAX(C19:F19),"Money Market","Put"))) -> Forward
A20: =A19+1 -> 2 | B20: =S0_in*(1+A20*STEP_FRAC) -> 1.175754 | C20: =B20*FC_AMT -> 23515080 | D20: =USD_FWD -> 23300438 | E20: =USD_MM -> 23300438 | F20: =MAX(B20,K_PUT)*FC_AMT-FV_PREMIUM_PUT -> 22890443 | G20: =D20-C20 -> -214642.12 | H20: =E20-C20 -> -214642.12 | I20: =F20-C20 -> -624637.5 | J20: =IF(C20=MAX(C20:F20),"No Hedge",IF(D20=MAX(C20:F20),"Forward",IF(E20=MAX(C20:F20),"Money Market","Put"))) -> No Hedge
A21: =A20+1 -> 3 | B21: =S0_in*(1+A21*STEP_FRAC) -> 1.187281 | C21: =B21*FC_AMT -> 23745620 | D21: =USD_FWD -> 23300438 | E21: =USD_MM -> 23300438 | F21: =MAX(B21,K_PUT)*FC_AMT-FV_PREMIUM_PUT -> 23120982 | G21: =D21-C21 -> -445182.12 | H21: =E21-C21 -> -445182.12 | I21: =F21-C21 -> -624637.5 | J21: =IF(C21=MAX(C21:F21),"No Hedge",IF(D21=MAX(C21:F21),"Forward",IF(E21=MAX(C21:F21),"Money Market","Put"))) -> No Hedge
A22: =A21+1 -> 4 | B22: =S0_in*(1+A22*STEP_FRAC) -> 1.198808 | C22: =B22*FC_AMT -> 23976160 | D22: =USD_FWD -> 23300438 | E22: =USD_MM -> 23300438 | F22: =MAX(B22,K_PUT)*FC_AMT-FV_PREMIUM_PUT -> 23351523 | G22: =D22-C22 -> -675722.12 | H22: =E22-C22 -> -675722.12 | I22: =F22-C22 -> -624637.5 | J22: =IF(C22=MAX(C22:F22),"No Hedge",IF(D22=MAX(C22:F22),"Forward",IF(E22=MAX(C22:F22),"Money Market","Put"))) -> No Hedge
A23: =A22+1 -> 5 | B23: =S0_in*(1+A23*STEP_FRAC) -> 1.210335 | C23: =B23*FC_AMT -> 24206700 | D23: =USD_FWD -> 23300438 | E23: =USD_MM -> 23300438 | F23: =MAX(B23,K_PUT)*FC_AMT-FV_PREMIUM_PUT -> 23582063 | G23: =D23-C23 -> -906262.12 | H23: =E23-C23 -> -906262.12 | I23: =F23-C23 -> -624637.5 | J23: =IF(C23=MAX(C23:F23),"No Hedge",IF(D23=MAX(C23:F23),"Forward",IF(E23=MAX(C23:F23),"Money Market","Put"))) -> No Hedge

Sheet Checks
A1: Validation Checks
A2: All checks must pass before Stage 4 market-data replacement
A4: Live Workbook Audit Controls
A5: Check | B5: Actual | C5: Expected | D5: Tolerance | E5: Status | F5: Where to fix | G5: Notes
A6: Forward vs. money-market parity | B6: =ABS(PARITY_GAP) -> 3.3527613e-08 | C6: 0 | D6: =PARITY_TOL -> 1 | E6: =IF(B6<=D6,"PASS","FAIL") -> PASS | F6: Inputs / Money Market | G6: Uses unrounded USD outcomes
A7: Forward is constant in grid | B7: =MAX(Sensitivity!D13:D23)-MIN(Sensitivity!D13:D23) -> 0 | C7: 0 | D7: 0 | E7: =IF(B7<=D7,"PASS","FAIL") -> PASS | F7: Sensitivity | G7: Max less min of forward column
A8: Money market is constant in grid | B8: =MAX(Sensitivity!E13:E23)-MIN(Sensitivity!E13:E23) -> 0 | C8: 0 | D8: 0 | E8: =IF(B8<=D8,"PASS","FAIL") -> PASS | F8: Sensitivity | G8: Max less min of money-market column
A9: No-hedge step equals exposure × grid step | B9: =ABS((Sensitivity!C14-Sensitivity!C13)-(FC_AMT*S0_in*STEP_FRAC)) -> 0 | C9: 0 | D9: 1 | E9: =IF(B9<=D9,"PASS","FAIL") -> PASS | F9: Sensitivity / Inputs | G9: Checks first two sensitivity rows
A10: Put base ties to Options tab | B10: =ABS(Sensitivity!F18-USD_PUT_BASE) -> 0 | C10: 0 | D10: 1 | E10: =IF(B10<=D10,"PASS","FAIL") -> PASS | F10: Options / Sensitivity | G10: Base row must match option base proceeds
A12: Overall Model Status
A13: MODEL STATUS | F13: =IF(COUNTIF(E6:E10,"FAIL")=0,"PASS","FAIL") -> PASS

Sheet Audit Summary
A1: Stage 3 Audit Summary
A2: Audit findings, fixes, and live workbook status — companion to analysis/2026-07-30-gennerman-build-audit.md
A4: Audit Status
A5: Audit item | B5: Live value
A6: Overall model status | B6: =Checks!F13 -> PASS
A7: Parity check | B7: =PARITY_CHECK -> PASS
A9: Findings, Fixes, and Evidence
A10: # | B10: What was checked | C10: Finding | D10: Correction | E10: Evidence | F10: Workbook location | G10: Status
A11: 1 | B11: Forward / money-market parity | C11: Original indicative forward placeholder was inconsistent with ACT/360 rates. | D11: Replaced it with the full covered-interest-parity value; it displays as 1.1273. | E11: Parity gap is effectively $0. | F11: Inputs; Money Market; Checks | G11: =Checks!F13 -> PASS
A12: 2 | B12: Put-floor trace | C12: Put floor originally pointed to the wrong sensitivity range. | D12: Linked USD_PUT_FLOOR to the USD_PUT sensitivity column. | E12: $21,372,625 matches the grid minimum. | F12: Options; Sensitivity | G12: =Checks!F13 -> PASS
A13: 3 | B13: Cover status link | C13: Cover referred to the wrong overall-status cell. | D13: Relinked Cover model status to the Checks tab. | E13: Cover and Checks both show PASS. | F13: Cover; Checks | G13: =Checks!F13 -> PASS
A14: 4 | B14: Formula descriptions | C14: Formula notes evaluated as formulas instead of displaying the audit logic. | D14: Converted formula descriptions to literal text; calculation cells remain formulas. | E14: Formula logic is readable on all calculation tabs. | F14: Forward; Money Market; Options | G14: =Checks!F13 -> PASS
A15: 5 | B15: Call S_T schedule | C15: Call was displayed only at the base case, not across settlement spots. | D15: Added an eleven-row call payoff and payable-outlay schedule linked to S_T. | E15: Call payoff and capped outlay recalculate from −5% to +5%. | F15: Options | G15: =Checks!F13 -> PASS

Sheet Notes & Assumptions
A1: Notes & Assumptions
A2: Source documentation, conventions, and Stage 4 refresh instructions
A5: Topic | B5: Documentation
A6: Quote convention | B6: All FX rates are USD per EUR. A higher rate means EUR appreciation and higher USD proceeds on the receivable.
A7: Interest convention | B7: Simple interest, ACT/360 for both the USD and EUR legs: 1 + rate × days / 360.
A8: Forward / MM parity | B8: Stage 4 F0_in is CIP-implied: S0_in × (1 + R_USD × T_DAYS/360) / (1 + R_FC × T_DAYS/360). The model therefore should pass parity within the $1 tolerance.
A9: Option premium | B9: Premium is paid in USD today per EUR of notional and carried to settlement at R_USD. No contract multiplier is assumed.
A10: Excluded items | B10: Counterparty risk, CVA, collateral, taxes, accounting designation, bid-ask, commissions, and transaction costs are excluded from the base case.
A11: Sensitivity | B11: Eleven formula-driven observations: -5% to +5% of S0_in in 1% steps. No probability weights are applied.
A12: Stage 4 population | B12: Sources and retrieval logic are documented in data/2026-08-02-gennerman-market-data.md. Use 2026-07-27 ECB EUR/USD spot, 2026-07-08 FRED DGS1, and ECB 2.25% deposit facility; option premia remain scenario assumptions.
